odp_stockholm/__init__.py
odp_stockholm/exceptions.py
odp_stockholm/models.py
odp_stockholm/odp_stockholm.py
odp_stockholm/py.typed
odp_stockholm-1.0.0.dist-info/LICENSE
odp_stockholm-1.0.0.dist-info/METADATA
odp_stockholm-1.0.0.dist-info/WHEEL
odp_stockholm-1.0.0.dist-info/RECORD
